alpine/__init__.py
alpine/exchanges/__init__.py
alpine/exchanges/abstract.py
alpine/exchanges/binance.py
alpine/exchanges/bitget.py
alpine/exchanges/utils.py
alpine/exchanges/wrapper.py
crypto_alpine-0.1.4.dist-info/LICENSE
crypto_alpine-0.1.4.dist-info/METADATA
crypto_alpine-0.1.4.dist-info/WHEEL
crypto_alpine-0.1.4.dist-info/RECORD
